Metadata-Version: 2.1
Name: menelaus
Version: 0.2.0
Summary: This library implements algorithms for detecting data drift and concept drift for ML and statistics applications.
Home-page: https://github.com/mitre/menelaus
Author: Leigh Nicholl, Thomas Schill, India Lindsay, Anmol Srivastava, Kodie P McNamara, Austin Downing
Author-email: tschill@mitre.org
License: Apache 2.0
Classifier: Intended Audience :: Developers
Classifier: Intended Audience :: Science/Research
Classifier: Topic :: Scientific/Engineering
Classifier: License :: OSI Approved :: Apache Software License
Classifier: Programming Language :: Python
Provides-Extra: test
Provides-Extra: dev
Provides-Extra: format
License-File: LICENSE.txt
